HISTORY.rst
LICENSE.rst
MANIFEST.in
README.rst
setup.py
src/yafowil/__init__.py
src/yafowil.werkzeug.egg-info/PKG-INFO
src/yafowil.werkzeug.egg-info/SOURCES.txt
src/yafowil.werkzeug.egg-info/dependency_links.txt
src/yafowil.werkzeug.egg-info/entry_points.txt
src/yafowil.werkzeug.egg-info/namespace_packages.txt
src/yafowil.werkzeug.egg-info/requires.txt
src/yafowil.werkzeug.egg-info/top_level.txt
src/yafowil.werkzeug.egg-info/zip-safe
src/yafowil/werkzeug/__init__.py