Metadata-Version: 1.1
Name: yafowil.werkzeug
Version: 0.1
Summary: Werkzeug Integration for YAFOWIL
Home-page: http://pypi.python.org/pypi/yafowil.werkzeug
Author: BlueDynamics Alliance
Author-email: dev@bluedynamics.com
License: Simplified BSD
Keywords: werkzeug request response html input widgets
Platform: UNKNOWN
Classifier: Operating System :: OS Independent
Classifier: Programming Language :: Python
Classifier: Topic :: Software Development
Classifier: Topic :: Internet :: WWW/HTTP :: Dynamic Content
Classifier: License :: OSI Approved :: BSD License
